indistinguishable_from_magic/__init__.py
indistinguishable_from_magic/magic.py
indistinguishable_from_magic-0.0.4.dist-info/METADATA
indistinguishable_from_magic-0.0.4.dist-info/WHEEL
indistinguishable_from_magic-0.0.4.dist-info/licenses/LICENSE
indistinguishable_from_magic-0.0.4.dist-info/RECORD
