Metadata-Version: 2.4
Name: indistinguishable_from_magic
Version: 0.0.4
Summary: Indistinguishable From Magic Python Package
Project-URL: Homepage, https://github.com/Indistinguishable-From-Magic/magic-py
Author-email: Indistinguishable From Magic <hello@ifmagic.io>
License-Expression: LicenseRef-IFM-EULA
License-File: LICENSE
Classifier: Operating System :: OS Independent
Classifier: Programming Language :: Python :: 3
Requires-Python: >=3.8
